NEMO_external_users/__init__.py
NEMO_external_users/admin.py
NEMO_external_users/apps.py
NEMO_external_users/backends.py
NEMO_external_users/forms.py
NEMO_external_users/models.py
NEMO_external_users/tests.py
NEMO_external_users/tokens.py
NEMO_external_users/urls.py
NEMO_external_users/views.py
NEMO_external_users/migrations/0001_version_0_0_1.py
NEMO_external_users/migrations/__init__.py
NEMO_external_users/templates/activate_account.html
NEMO_external_users/templates/authenticate/create_account.html
NEMO_external_users/templates/authenticate/login.html
NEMO_external_users/templates/base/navbar_base.html
nemo_external_users-0.1.0.dist-info/METADATA
nemo_external_users-0.1.0.dist-info/WHEEL
nemo_external_users-0.1.0.dist-info/licenses/LICENSE
nemo_external_users-0.1.0.dist-info/RECORD
