Metadata-Version: 2.1
Name: NEMO-external-users
Version: 0.1.0
Summary: NEMO plugin allowing users to create and manage their own accounts.
Project-URL: Homepage, https://github.com/maakleerplek/NEMO-external-users
Author-email: High Tech Lab <hightechlab@maakleerplekleuven.be>
Maintainer-email: Michal Machnicki <michal.machnicki@maakleerplekleuven.be>
License: MIT License
License-File: LICENSE
Classifier: Environment :: Web Environment
Classifier: Intended Audience :: Science/Research
Classifier: Intended Audience :: System Administrators
Classifier: License :: OSI Approved :: MIT License
Classifier: Natural Language :: English
Classifier: Operating System :: OS Independent
Classifier: Programming Language :: Python
Classifier: Programming Language :: Python :: 3
Classifier: Programming Language :: Python :: 3 :: Only
Classifier: Programming Language :: Python :: 3.8
Classifier: Topic :: Internet :: WWW/HTTP
Classifier: Topic :: Internet :: WWW/HTTP :: Dynamic Content
Requires-Python: >=3.8
